{
  "main": {
    "id": "b04d595ed570ae0f",
    "type": "split",
    "children": [
      {
        "id": "b6b0793d674ae7bd",
        "type": "tabs",
        "children": [
          {
            "id": "9fb6d62d390bee4f",
            "type": "leaf",
            "state": {
              "type": "markdown",
              "state": {
                "file": "JavaScript/Interview Preps.md",
                "mode": "source",
                "source": false
              }
            }
          },
          {
            "id": "fb526db54b56d8df",
            "type": "leaf",
            "state": {
              "type": "markdown",
              "state": {
                "file": "JavaScript/React/Mental Model.md",
                "mode": "source",
                "source": false
              }
            }
          },
          {
            "id": "3b3daca281f069eb",
            "type": "leaf",
            "state": {
              "type": "markdown",
              "state": {
                "file": "JavaScript/Nestjs/nestjs.md",
                "mode": "source",
                "source": false
              }
            }
          },
          {
            "id": "1b6d72578d68dbee",
            "type": "leaf",
            "state": {
              "type": "markdown",
              "state": {
                "file": "JavaScript/Nestjs/Introduction.md",
                "mode": "source",
                "source": false
              }
            }
          }
        ],
        "currentTab": 3
      }
    ],
    "direction": "vertical"
  },
  "left": {
    "id": "5f828e6113cc047f",
    "type": "split",
    "children": [
      {
        "id": "e70bde42af28cda7",
        "type": "tabs",
        "children": [
          {
            "id": "8c5dcb841411d815",
            "type": "leaf",
            "state": {
              "type": "file-explorer",
              "state": {
                "sortOrder": "alphabetical"
              }
            }
          },
          {
            "id": "e34e75e637df7f5c",
            "type": "leaf",
            "state": {
              "type": "search",
              "state": {
                "query": "",
                "matchingCase": false,
                "explainSearch": false,
                "collapseAll": false,
                "extraContext": false,
                "sortOrder": "alphabetical"
              }
            }
          },
          {
            "id": "c9b1f525d12470b0",
            "type": "leaf",
            "state": {
              "type": "bookmarks",
              "state": {}
            }
          }
        ]
      }
    ],
    "direction": "horizontal",
    "width": 200
  },
  "right": {
    "id": "fd0dfcc9b3566824",
    "type": "split",
    "children": [
      {
        "id": "8e8938b619e881e2",
        "type": "tabs",
        "children": [
          {
            "id": "0f3f5d4d81379374",
            "type": "leaf",
            "state": {
              "type": "backlink",
              "state": {
                "file": "JavaScript/Nestjs/Introduction.md",
                "collapseAll": false,
                "extraContext": false,
                "sortOrder": "alphabetical",
                "showSearch": false,
                "searchQuery": "",
                "backlinkCollapsed": false,
                "unlinkedCollapsed": true
              }
            }
          },
          {
            "id": "0d81cbe26bed4c62",
            "type": "leaf",
            "state": {
              "type": "outgoing-link",
              "state": {
                "file": "JavaScript/Nestjs/Introduction.md",
                "linksCollapsed": false,
                "unlinkedCollapsed": true
              }
            }
          },
          {
            "id": "8134578adc5cc07b",
            "type": "leaf",
            "state": {
              "type": "tag",
              "state": {
                "sortOrder": "frequency",
                "useHierarchy": true
              }
            }
          },
          {
            "id": "25094d7b89eb4b67",
            "type": "leaf",
            "state": {
              "type": "outline",
              "state": {
                "file": "JavaScript/Nestjs/Introduction.md"
              }
            }
          }
        ]
      }
    ],
    "direction": "horizontal",
    "width": 300,
    "collapsed": true
  },
  "left-ribbon": {
    "hiddenItems": {
      "switcher:Open quick switcher": false,
      "graph:Open graph view": false,
      "canvas:Create new canvas": false,
      "daily-notes:Open today's daily note": false,
      "templates:Insert template": false,
      "command-palette:Open command palette": false
    }
  },
  "active": "1b6d72578d68dbee",
  "lastOpenFiles": [
    "JavaScript/Nestjs/nestjs.md",
    "JavaScript/Nestjs/Introduction.md",
    "Introduction.md",
    "JavaScript/TS/Mental Model.md",
    "JavaScript/Nestjs",
    "JavaScript/TS.md",
    "JavaScript/React/Mental Model.md",
    "JavaScript/Interview Preps.md",
    "ternary.png",
    "JavaScript/JS/Bind-call-apply.md",
    "JavaScript/React/Mental Modal.md",
    "JavaScript/Node/index.js.md",
    "JavaScript/JS/Asynchronous Programming.md",
    "JavaScript/JS/Anki.md",
    "JavaScript/Node/Intro.md",
    "JavaScript/State Management/Mental Model.md",
    "Briefings/2023-11-17 kimon.md",
    "JavaScript/Node",
    "JavaScript/State Management/Redux/redux.md",
    "2023-11-16 - 1on1-with.md",
    "Projects/Meta Spark AR/Main Note.md",
    "Briefings/2023-11-08-with-George.md",
    "Other Course/Gen AI/Introduction to generative AI.md",
    "ANN.png",
    "Gen Ml.png",
    "unsupervised.png",
    "supervised.png",
    "ml.png",
    "Other Course/Gen AI/generative AI.md",
    "Other Course/Gen AI",
    "Other Course",
    "Projects/Meta Spark AR",
    "JavaScript/State Management/ContextAPI/contextAPI.md",
    "Projects/Moni Share/Code reviews feedback sharing.md",
    "Projects/Moni Share/QA Review.md",
    "Projects/Moni Share/Final Review.md",
    "Projects/Moni Share/Mid Review - Sprint 1.md",
    "JavaScript/State Management/ContextAPI",
    "JavaScript/State Management/Redux",
    "JavaScript/State Management",
    "Projects/Restaurent",
    "Daily"
  ]
}